neural_diffeqs/__init__.py
neural_diffeqs/__version__.py
neural_diffeqs/_latent_potential_ode.py
neural_diffeqs/_latent_potential_sde.py
neural_diffeqs/_neural_ode.py
neural_diffeqs/_neural_sde.py
neural_diffeqs/_potential_ode.py
neural_diffeqs/_potential_sde.py
neural_diffeqs/core/__init__.py
neural_diffeqs/core/_base_latent_ode.py
neural_diffeqs/core/_base_latent_sde.py
neural_diffeqs/core/_base_neural_diffeq.py
neural_diffeqs/core/_base_neural_ode.py
neural_diffeqs/core/_base_neural_sde.py
neural_diffeqs/core/_diffeq_config.py
neural_diffeqs/core/_potential.py
neural_diffeqs-0.4.1.dist-info/LICENSE
neural_diffeqs-0.4.1.dist-info/METADATA
neural_diffeqs-0.4.1.dist-info/WHEEL
neural_diffeqs-0.4.1.dist-info/top_level.txt
neural_diffeqs-0.4.1.dist-info/RECORD
