Metadata-Version: 2.2
Name: neural-diffeqs
Version: 0.4.1
Summary: Neural differential equations made easy.
Author: Michael E. Vinyard
Author-email: mvinyard@broadinstitute.org
License: MIT
Classifier: Development Status :: 2 - Pre-Alpha
Classifier: Programming Language :: Python :: 3.9
Classifier: Intended Audience :: Science/Research
Classifier: Topic :: Scientific/Engineering :: Bio-Informatics
Requires-Python: >3.9.0
License-File: LICENSE
Requires-Dist: numpy
Requires-Dist: torch
Requires-Dist: torch-nets
Requires-Dist: torchsde
Dynamic: author
Dynamic: author-email
Dynamic: classifier
Dynamic: description
Dynamic: description-content-type
Dynamic: license
Dynamic: requires-dist
Dynamic: requires-python
Dynamic: summary
